deeplot/__init__.py
deeplot/deeplot.py
deeplot/architecture/AlexNet_A.png
deeplot/architecture/AlexNet_B.png
deeplot/architecture/CNN architecture.png
deeplot/architecture/DenseNetArch.jpg
deeplot/architecture/DenseNetArch2.jpg
deeplot/architecture/DenseNetOverview.jpg
deeplot/architecture/DenseNetOverview2.jpg
deeplot/architecture/GoogleNet.png
deeplot/architecture/GoogleNetAux.png
deeplot/architecture/InceptionModule.png
deeplot/architecture/InvertedResidual.jpg
deeplot/architecture/LeNet5_A.png
deeplot/architecture/LeNet5_B.png
deeplot/architecture/MLP.png
deeplot/architecture/MobilenetArch.jpg
deeplot/architecture/MobilenetBlock.jpg
deeplot/architecture/NumberOfParameters.png
deeplot/architecture/Perceptron.png
deeplot/architecture/PlainvsResidual.png
deeplot/architecture/ResNetsLayers.png
deeplot/architecture/ResNextArchitecture.jpg
deeplot/architecture/ResNextV.jpg
deeplot/architecture/ResNextVariants.png
deeplot/architecture/Residual_blocks.png
deeplot/architecture/TLU.png
deeplot/architecture/VGG.png
deeplot/architecture/VGG_B.png
deeplot/architecture/__init__.py
deeplot-0.0.6.dist-info/LICENSE
deeplot-0.0.6.dist-info/METADATA
deeplot-0.0.6.dist-info/WHEEL
deeplot-0.0.6.dist-info/top_level.txt
deeplot-0.0.6.dist-info/RECORD
