Metadata-Version: 2.1
Name: deeplot
Version: 0.0.6
Summary: a tool to visualize ML/AI/NN architectures
Home-page: https://github.com/SimeraAI/deeplot
Author: Kolade Gideon (Allaye)
Author-email: allaye@allaye.com
License: UNKNOWN
Project-URL: Bug Tracker, https://github.com/SimeraAI/deeplot/issues
Platform: UNKNOWN
Classifier: Programming Language :: Python :: 3
Classifier: License :: OSI Approved :: MIT License
Classifier: Operating System :: OS Independent
Requires-Python: >=3.7
License-File: LICENSE
Requires-Dist: matplotlib
Requires-Dist: opencv-python
